monzo_utils/lib/__init__.py
monzo_utils/lib/config.py
monzo_utils/lib/db.py
monzo_utils/lib/log.py
monzo_utils/lib/monzo_api.py
monzo_utils/lib/monzo_payments.py
monzo_utils/lib/monzo_sync.py
monzo_utils/lib/singleton.py
monzo_utils/lib/transactions_seen.py
monzo_utils/lib/db_driver/__init__.py
monzo_utils/lib/db_driver/mysql.py
monzo_utils/lib/db_driver/sqlite.py
monzo_utils/model/__init__.py
monzo_utils/model/account.py
monzo_utils/model/amazon_payments.py
monzo_utils/model/base.py
monzo_utils/model/card_payment.py
monzo_utils/model/counterparty.py
monzo_utils/model/direct_debit.py
monzo_utils/model/finance.py
monzo_utils/model/flex.py
monzo_utils/model/flex_summary.py
monzo_utils/model/merchant.py
monzo_utils/model/merchant_address.py
monzo_utils/model/payment.py
monzo_utils/model/pot.py
monzo_utils/model/provider.py
monzo_utils/model/refund.py
monzo_utils/model/standing_order.py
monzo_utils/model/transaction.py
monzo_utils/model/transaction_metadata.py
monzo_utils-0.1.7.data/scripts/monzo-payments
monzo_utils-0.1.7.data/scripts/monzo-search
monzo_utils-0.1.7.data/scripts/monzo-status
monzo_utils-0.1.7.data/scripts/monzo-sync
monzo_utils-0.1.7.dist-info/LICENSE
monzo_utils-0.1.7.dist-info/METADATA
monzo_utils-0.1.7.dist-info/WHEEL
monzo_utils-0.1.7.dist-info/top_level.txt
monzo_utils-0.1.7.dist-info/RECORD
